primosjosearredondo/__init__.py
primosjosearredondo-1.0.dist-info/LICENSE
primosjosearredondo-1.0.dist-info/METADATA
primosjosearredondo-1.0.dist-info/WHEEL
primosjosearredondo-1.0.dist-info/top_level.txt
primosjosearredondo-1.0.dist-info/RECORD
